oracle4grid/__init__.py
oracle4grid/main.py
oracle4grid/core/__init__.py
oracle4grid/core/oracle.py
oracle4grid/core/actions_utils/__init__.py
oracle4grid/core/actions_utils/combinator.py
oracle4grid/core/agent/OneChangeThenOnlyReconnect.py
oracle4grid/core/agent/OracleAgent.py
oracle4grid/core/agent/OracleL2RPNReward.py
oracle4grid/core/agent/OracleOverloadReward.py
oracle4grid/core/agent/__init__.py
oracle4grid/core/graph/__init__.py
oracle4grid/core/graph/attack_graph_module.py
oracle4grid/core/graph/compute_trajectory.py
oracle4grid/core/graph/graph_generator.py
oracle4grid/core/graph/indicators.py
oracle4grid/core/replay/__init__.py
oracle4grid/core/replay/agent_replay.py
oracle4grid/core/reward_computation/Run.py
oracle4grid/core/reward_computation/__init__.py
oracle4grid/core/reward_computation/attacks_multiverse.py
oracle4grid/core/reward_computation/run_many.py
oracle4grid/core/reward_computation/run_one.py
oracle4grid/core/utils/Action.py
oracle4grid/core/utils/__init__.py
oracle4grid/core/utils/actions_generator.py
oracle4grid/core/utils/config_ini_utils.py
oracle4grid/core/utils/constants.py
oracle4grid/core/utils/launch_utils.py
oracle4grid/core/utils/prepare_environment.py
oracle4grid/core/utils/serialization.py
oracle4grid/test/Test_Agent_Replay_save_reload.py
oracle4grid/test/__init__.py
oracle4grid/test/graph_validity_test.py
oracle4grid/test/integration_test.py
oracle4grid/test/performance_test.py
Oracle4Grid-1.0.6.dist-info/LICENSE
Oracle4Grid-1.0.6.dist-info/LICENSE.md
Oracle4Grid-1.0.6.dist-info/METADATA
Oracle4Grid-1.0.6.dist-info/WHEEL
Oracle4Grid-1.0.6.dist-info/entry_points.txt
Oracle4Grid-1.0.6.dist-info/top_level.txt
Oracle4Grid-1.0.6.dist-info/RECORD
